pygetent/__init__.py
pygetent/constants.py
pygetent/headers.py
pygetent/libc.py
pygetent-0.1.dist-info/LICENSE
pygetent-0.1.dist-info/METADATA
pygetent-0.1.dist-info/WHEEL
pygetent-0.1.dist-info/top_level.txt
pygetent-0.1.dist-info/RECORD
