Metadata-Version: 2.1
Name: pygetent
Version: 0.1
Summary: POSIX getent syscalls in python
Author: ScreamingPigeon
Author-email: screamingpigeon <visitprakhar@gmail.com>
Project-URL: Homepage, https://github.com/screamingpigeon/xalt
Classifier: Programming Language :: Python :: 3
Classifier: License :: OSI Approved :: GNU General Public License v3 (GPLv3)
Requires-Python: >=3.8
License-File: LICENSE
